aicodetools/__init__.py
aicodetools/client.py
aicodetools/client_manager.py
aicodetools/filters.py
aicodetools/server.py
aicodetools/tools/__init__.py
aicodetools/tools/edit.py
aicodetools/tools/read.py
aicodetools/tools/run.py
aicodetools/tools/write.py
aicodetools-2.0.53.dist-info/LICENSE
aicodetools-2.0.53.dist-info/METADATA
aicodetools-2.0.53.dist-info/WHEEL
aicodetools-2.0.53.dist-info/RECORD
