Metadata-Version: 2.3
Name: aicodetools
Version: 2.0.53
Summary: Simple, lightweight AI code tools with Docker-only support - no complex dependencies
License: MIT
Keywords: artificial intelligence,ai agents,code tools,docker,simple
Author: balajidinesh
Requires-Python: >=3.10,<4.0
Classifier: Development Status :: 4 - Beta
Classifier: Intended Audience :: Developers
Classifier: License :: OSI Approved :: MIT License
Classifier: Programming Language :: Python :: 3
Classifier: Programming Language :: Python :: 3.10
Classifier: Programming Language :: Python :: 3.11
Classifier: Programming Language :: Python :: 3.12
Classifier: Programming Language :: Python :: 3.13
Classifier: Topic :: Scientific/Engineering :: Artificial Intelligence
Requires-Dist: pydantic (>=2.0.0,<3.0.0)
Requires-Dist: requests (>=2.28.0,<3.0.0)
Requires-Dist: tiktoken (>=0.11.0,<0.12.0)
Project-URL: Documentation, https://github.com/balajidinesh/aicodetools
Project-URL: Homepage, https://github.com/balajidinesh/aicodetools
Project-URL: Repository, https://github.com/balajidinesh/aicodetools
